Workbook

Sheet Employees
A1: BusinessEntityID | B1: NationalIDNumber | C1: LoginID | D1: OrganizationLevel | E1: JobTitle | F1: BirthDate | G1: MaritalStatus | H1: HireDate | I1: SalariedFlag | J1: VacationHours | K1: SickLeaveHours | L1: Salary
A2: 1 | B2: 295847284 | C2: ken0 | D2: 0 | E2: Chief Executive Officer | F2: 28882 | G2: S | H2: 43477 | I2: 1 | J2: 99 | K2: 69 | L2: 1500000
A3: 2 | B3: 658797903 | C3: gigi0 | D3: 4 | E3: Research and Development Engineer | F3: 32526 | G3: M | H3: 43479 | I3: 1 | J3: 63 | K3: 51 | L3: 109946
A4: 3 | B4: 811994146 | C4: diane1 | D4: 4 | E4: Research and Development Engineer | F4: 35218 | G4: S | H4: 43461 | I4: 1 | J4: 62 | K4: 51 | L4: 88314
A5: 4 | B5: 134969118 | C5: dylan0 | D5: 3 | E5: Research and Development Manager | F5: 35482 | G5: M | H5: 43502 | I5: 1 | J5: 61 | K5: 50 | L5: 184553
A6: 5 | B6: 112457891 | C6: rob0 | D6: 3 | E6: Senior Tool Designer | F6: 31036 | G6: S | H6: 43071 | I6: 0 | J6: 48 | K6: 80 | L6: 112876
A7: 6 | B7: 879342154 | C7: michael6 | D7: 4 | E7: Research and Development Manager | F7: 34666 | G7: M | H7: 43586 | I7: 1 | J7: 16 | K7: 64 | L7: 61876
A8: 7 | B8: 974026903 | C8: ovidiu0 | D8: 3 | E8: Senior Tool Designer | F8: 32157 | G8: S | H8: 44167 | I8: 0 | J8: 7 | K8: 23 | L8: 128399
A9: 8 | B9: 998320692 | C9: jossef0 | D9: 3 | E9: Design Engineer | F9: 25270 | G9: M | H9: 43121 | I9: 1 | J9: 6 | K9: 23 | L9: 184037
A10: 9 | B10: 695256908 | C10: gail0 | D10: 3 | E10: Design Engineer | F10: 22914 | G10: M | H10: 43103 | I10: 1 | J10: 5 | K10: 22 | L10: 143468
A11: 10 | B11: 509647174 | C11: roberto0 | D11: 2 | E11: Engineering Manager | F11: 30995 | G11: M | H11: 43047 | I11: 1 | J11: 2 | K11: 21 | L11: 206812
A12: 11 | B12: 245797967 | C12: terri0 | D12: 1 | E12: Vice President of Engineering | F12: 29796 | G12: S | H12: 43128 | I12: 1 | J12: 1 | K12: 20 | L12: 624024
A13: 12 | B13: 480168528 | C13: thierry0 | D13: 4 | E13: Tool Designer | F13: 25410 | G13: M | H13: 43077 | I13: 0 | J13: 9 | K13: 24 | L13: 92185
... A292: 291 | B292: 712885347 | C292: jeff0 | D292: 3 | E292: Production Supervisor - WC45 | F292: 31790 | G292: M | H292: 43484 | I292: 0 | J292: 74 | K292: 57 | L292: 156035

Sheet Employee Summary
A1: OrganizationLevel
A3: OrganizationLevel | B3: Hierarchy Description | C3: Number of Employees | D3: Total Salary | E3: Average Salary | F3: % Increase | G3: New Salary
A4: 0 | B4: Leadership Team | C4: =COUNTIFS(Employees!D$2:D$292,$A4) -> 1 | D4: =SUMIFS(Employees!$L$2:$L$292,Employees!D$2:D$292,$A4) -> 1500000 | E4: =D4/C4 -> 1500000 | F4: 0.05 | G4: =D4*(1+F4) -> 1575000
A5: 1 | B5: Leadership Team | C5: =COUNTIFS(Employees!D$2:D$292,$A5) -> 6 | D5: =SUMIFS(Employees!$L$2:$L$292,Employees!D$2:D$292,$A5) -> 4042296 | E5: =D5/C5 -> 673716 | F5: =F4+1% -> 0.06 | G5: =D5*(1+F5) -> 4284833.8
A6: 2 | B6: Senior Management | C6: =COUNTIFS(Employees!D$2:D$292,$A6) -> 27 | D6: =SUMIFS(Employees!$L$2:$L$292,Employees!D$2:D$292,$A6) -> 6151709 | E6: =D6/C6 -> 227841.07 | F6: =F5+1% -> 0.07 | G6: =D6*(1+F6) -> 6582328.6
A7: 3 | B7: Middle Management | C7: =COUNTIFS(Employees!D$2:D$292,$A7) -> 67 | D7: =SUMIFS(Employees!$L$2:$L$292,Employees!D$2:D$292,$A7) -> 10130857 | E7: =D7/C7 -> 151206.82 | F7: =F6+1% -> 0.08 | G7: =D7*(1+F7) -> 10941326
A8: 4 | B8: Frontline Staff | C8: =COUNTIFS(Employees!D$2:D$292,$A8) -> 190 | D8: =SUMIFS(Employees!$L$2:$L$292,Employees!D$2:D$292,$A8) -> 16572702 | E8: =D8/C8 -> 87224.747 | F8: =F7+1% -> 0.09 | G8: =D8*(1+F8) -> 18064245
A9: Total | C9: 291 | D9: =SUM(D4:D8) -> 38397564 | G9: =SUM(G4:G8) -> 41447733

Sheet Filter
A1: BusinessEntityID | B1: NationalIDNumber | C1: LoginID | D1: OrganizationLevel | E1: JobTitle | F1: BirthDate | G1: MaritalStatus | H1: HireDate | I1: SalariedFlag | J1: VacationHours | K1: SickLeaveHours | L1: Salary

Sheet Workday
A1: Workday | E1: Vacation
A3: Starting date | B3: 46266 | E3: 46270
A4: Number of days | B4: 15 | E4: 46271
A5: Ending date | E5: 46272
E6: 46273
E7: 46274
E8: 46275
E9: 46276
E10: 46277
E11: 46278

Sheet Hire Date
A1: Hire Date and Awards
A3: Hire Date | B3: Award Description
A4: 42370 | B4: May be eligible for gold service level award
A5: 43101 | B5: May be eligible for silver service level award
A6: 43831 | B6: May be eligible for bronze service level award
A7: 44562 | B7: Not yet eligible

Sheet Sunburst
A1: Sunburst
A3: Year | B3: Quarter | C3: Month | D3: Total Invoiced
A4: 2021 | D4: 14155700
A5: 2022 | B5: Qtr1 | D5: 9443736.8
A6: 2022 | B6: Qtr2 | C6: Apr | D6: 1871923.5
A7: 2022 | B7: Qtr2 | C7: May | D7: 3452924.5
A8: 2022 | B8: Qtr2 | C8: Jun | D8: 4610647.2
A9: 2022 | B9: Qtr3 | D9: 10164407
A10: 2022 | B10: Qtr4 | D10: 8132061.5
A11: 2023 | D11: 48965888
A12: 2024 | D12: 22419498
A13: Grand Total | D13: 1.2321679e+08

Sheet Waterfall
A1: Waterfall
A3: Year/Quarter | B3: Total Invoiced
A4: 2021Q2 | B4: 1074117.4 | C4: =B4 -> 1074117.4
A5: 2021Q3 | B5: 5647550.7 | C5: =B5-B4 -> 4573433.2
A6: 2021Q4 | B6: 7434031.4 | C6: =B6-B5 -> 1786480.8
A7: 2022Q1 | B7: 9443736.8 | C7: =B7-B6 -> 2009705.4
A8: 2022Q2 | B8: 9935495.2 | C8: =B8-B7 -> 491758.36
A9: 2022Q3 | B9: 10164407 | C9: =B9-B8 -> 228911.66
A10: 2022Q4 | B10: 8132061.5 | C10: =B10-B9 -> -2032345.3
A11: 2023Q1 | B11: 8771886.4 | C11: =B11-B10 -> 639824.86
A12: 2023Q2 | B12: 12225061 | C12: =B12-B11 -> 3453175
A13: 2023Q3 | B13: 14339319 | C13: =B13-B12 -> 2114257.8
A14: 2023Q4 | B14: 13629621 | C14: =B14-B13 -> -709698.15
A15: 2024Q1 | B15: 14373277 | C15: =B15-B14 -> 743656.44
A16: 2024Q2 | B16: 8046220.8 | C16: =B16-B15 -> -6327056.6
A17: Total | B17: =SUM(B4:B16) -> 1.2321679e+08

Sheet Sales
A1: OrderDate | B1: TotalDue
A2: 40694 | B2: 567020.95
A3: 40695 | B3: 15394.33
A4: 40696 | B4: 16588.457
A5: 40697 | B5: 7907.9768
A6: 40698 | B6: 16588.457
A7: 40699 | B7: 15815.954
A8: 40700 | B8: 8680.4804
A9: 40701 | B9: 8680.4804
A10: 40702 | B10: 23105.307
A11: 40703 | B11: 11664.966
A12: 40704 | B12: 15815.954
A13: 40705 | B13: 15618.954
... A1125: 41820 | B1125: 2921.1901
